slack_votebot-0.0.1a3.dist-info/DESCRIPTION.rst
slack_votebot-0.0.1a3.dist-info/METADATA
slack_votebot-0.0.1a3.dist-info/RECORD
slack_votebot-0.0.1a3.dist-info/WHEEL
slack_votebot-0.0.1a3.dist-info/metadata.json
slack_votebot-0.0.1a3.dist-info/top_level.txt
votebot/__init__.py
votebot/__main__.py
votebot/api.py
votebot/bot.py
votebot/config.py
votebot/utils.py
