Metadata-Version: 2.0
Name: slack-votebot
Version: 0.0.1a3
Summary: Voting bot for Slack.
Home-page: UNKNOWN
Author: Yoan Blanc
Author-email: yoan@dosimple.ch
License: https://opensource.org/licenses/BSD-3-Clause
Keywords: slack asyncio bot
Platform: UNKNOWN
Classifier: Development Status :: 2 - Pre-Alpha
Classifier: Environment :: Console
Classifier: Intended Audience :: Education
Classifier: License :: Free For Educational Use
Classifier: Operating System :: POSIX :: Linux
Classifier: Programming Language :: Python :: 3.4
Classifier: Programming Language :: Python :: 3.5
Classifier: Programming Language :: Python :: 3 :: Only
Requires-Dist: aiohttp
Provides-Extra: docs
Requires-Dist: sphinx; extra == 'docs'
Provides-Extra: fast
Requires-Dist: cchardet; extra == 'fast'
Provides-Extra: tests
Requires-Dist: asynctest; extra == 'tests'
Requires-Dist: pydocstyle; extra == 'tests'
Requires-Dist: pytest (>=2.8); extra == 'tests'
Requires-Dist: pytest-asyncio; extra == 'tests'
Requires-Dist: pytest-coverage; extra == 'tests'
Requires-Dist: pytest-flake8; extra == 'tests'
Requires-Dist: pytest-isort; extra == 'tests'
